triangulator/__init__.py
triangulator/ear_clipping_method.py
triangulator/geometry/__init__.py
triangulator/geometry/angles.py
triangulator/geometry/points.py
triangulator-1.0.3.dist-info/METADATA
triangulator-1.0.3.dist-info/WHEEL
triangulator-1.0.3.dist-info/top_level.txt
triangulator-1.0.3.dist-info/RECORD
